<?xml version="1.0" encoding="UTF-8"?>
<databaseChangeLog
    xmlns="http://www.liquibase.org/xml/ns/dbchangelog"
    xmlns:xsi="http://www.w3.org/2001/XMLSchema-instance"
    xsi:schemaLocation="
      http://www.liquibase.org/xml/ns/dbchangelog
      http://www.liquibase.org/xml/ns/dbchangelog/dbchangelog-4.3.xsd">

    <!-- Seed data for lesson_types table -->
    <changeSet id="106-seed-lesson-types" author="ktc">
        <insert tableName="lesson_types">
            <column name="id" value="type-001"/>
            <column name="name" value="VIDEO"/>
        </insert>
        <insert tableName="lesson_types">
            <column name="id" value="type-002"/>
            <column name="name" value="QUIZ"/>
        </insert>
    </changeSet>

</databaseChangeLog>
